importcontext/__init__.py
importcontext/import_context.py
importcontext-0.1.2.dist-info/METADATA
importcontext-0.1.2.dist-info/WHEEL
importcontext-0.1.2.dist-info/RECORD
