Metadata-Version: 2.3
Name: importcontext
Version: 0.1.2
Summary: 
Author: genderlesspit
Author-email: 59433707+genderlesspit@users.noreply.github.com
Requires-Python: >=3.13,<4.0
Classifier: Programming Language :: Python :: 3
Classifier: Programming Language :: Python :: 3.13
Requires-Dist: loguru (>=0.7.3,<0.8.0)
